Metadata-Version: 2.1
Name: torch-multi-head-attention
Version: 0.15.1
Summary: Multi-head attention implemented in PyTorch
Home-page: https://github.com/CyberZHG/torch-multi-head-attention
Author: CyberZHG
Author-email: CyberZHG@gmail.com
License: MIT
Platform: UNKNOWN
Classifier: Programming Language :: Python :: 2.7
Classifier: Programming Language :: Python :: 3.6
Classifier: License :: OSI Approved :: MIT License
Classifier: Operating System :: OS Independent
